{
  "scenario": "small_closed",
  "open_schools": [
    "Brown",
    "Dyer",
    "Skillin",
    "Kaler"
  ],
  "total_walkable_population": 14507,
  "total_walkable_students": 578.0,
  "total_non_walkable_students": 434.0,
  "pct_walkable": 57.1,
  "avg_drive_distance_m": 1943.0,
  "avg_drive_distance_mi": 1.207,
  "avg_drive_non_walkable_m": 2852.4,
  "avg_drive_non_walkable_mi": 1.772,
  "max_drive_distance_m": 5542.1,
  "max_drive_distance_mi": 3.444,
  "capacity_overflow": 0.0,
  "capacity_feasible": true,
  "zone_contiguity": {
    "Dyer": false,
    "Kaler": false,
    "Brown": false,
    "Skillin": false
  },
  "all_zones_contiguous": false,
  "school_metrics": {
    "Brown": {
      "school_id": "Brown",
      "assigned_population": 8289,
      "assigned_students": 251.4,
      "capacity": 260,
      "utilization_rate": 0.967,
      "capacity_overflow": 0.0,
      "pct_walkable": 83.5,
      "walkable_population": 6639,
      "walkable_students": 209.9,
      "non_walkable_students": 41.6,
      "avg_walk_distance_m": 1350.8,
      "avg_drive_distance_m": 1166.7,
      "avg_drive_distance_non_walkable_m": 1638.2,
      "max_drive_distance_m": 2002.6,
      "avg_drive_distance_mi": 0.725,
      "max_drive_distance_mi": 1.244,
      "avg_drive_non_walkable_mi": 1.018
    },
    "Dyer": {
      "school_id": "Dyer",
      "assigned_population": 5499,
      "assigned_students": 199.7,
      "capacity": 240,
      "utilization_rate": 0.832,
      "capacity_overflow": 0.0,
      "pct_walkable": 51.6,
      "walkable_population": 1983,
      "walkable_students": 103.0,
      "non_walkable_students": 96.6,
      "avg_walk_distance_m": 3043.5,
      "avg_drive_distance_m": 3015.1,
      "avg_drive_distance_non_walkable_m": 4198.2,
      "max_drive_distance_m": 5542.1,
      "avg_drive_distance_mi": 1.873,
      "max_drive_distance_mi": 3.444,
      "avg_drive_non_walkable_mi": 2.609
    },
    "Skillin": {
      "school_id": "Skillin",
      "assigned_population": 7958,
      "assigned_students": 374.2,
      "capacity": 380,
      "utilization_rate": 0.985,
      "capacity_overflow": 0.0,
      "pct_walkable": 43.2,
      "walkable_population": 3444,
      "walkable_students": 161.6,
      "non_walkable_students": 212.7,
      "avg_walk_distance_m": 1618.8,
      "avg_drive_distance_m": 1594.5,
      "avg_drive_distance_non_walkable_m": 2024.5,
      "max_drive_distance_m": 2837.0,
      "avg_drive_distance_mi": 0.991,
      "max_drive_distance_mi": 1.763,
      "avg_drive_non_walkable_mi": 1.258
    },
    "Kaler": {
      "school_id": "Kaler",
      "assigned_population": 4522,
      "assigned_students": 186.7,
      "capacity": 240,
      "utilization_rate": 0.778,
      "capacity_overflow": 0.0,
      "pct_walkable": 55.5,
      "walkable_population": 2441,
      "walkable_students": 103.5,
      "non_walkable_students": 83.1,
      "avg_walk_distance_m": 2255.6,
      "avg_drive_distance_m": 1995.6,
      "avg_drive_distance_non_walkable_m": 3548.8,
      "max_drive_distance_m": 4747.4,
      "avg_drive_distance_mi": 1.24,
      "max_drive_distance_mi": 2.95,
      "avg_drive_non_walkable_mi": 2.205
    }
  }
}